covmetrics/ERT.py
covmetrics/__about__.py
covmetrics/__init__.py
covmetrics/check.py
covmetrics/classifiers.py
covmetrics/dependence_metrics.py
covmetrics/group_metrics.py
covmetrics/losses.py
covmetrics/slab_metrics.py
covmetrics/utils.py
covmetrics-0.1.1.dist-info/METADATA
covmetrics-0.1.1.dist-info/WHEEL
covmetrics-0.1.1.dist-info/licenses/LICENCE
covmetrics-0.1.1.dist-info/RECORD
