Metadata-Version: 2.4
Name: covmetrics
Version: 0.1.1
Summary: Metrics for conditional coverage estimation
Project-URL: Documentation, https://github.com/ElSacho/covmetrics#README
Project-URL: Issues, https://github.com/ElSacho/covmetrics/issues
Project-URL: Source, https://github.com/ElSacho/covmetrics
Author-email: Sacha Braun <firstname.lastname@inria.fr>, David Holzmüller <firstname.lastname@inria.fr>
License: Copyright 2025, Sacha Braun, David Holzmüller
License-File: LICENCE
Keywords: Conditional,Conformal,Coverage,Diagnostic,Metrics
Classifier: Development Status :: 4 - Beta
Classifier: License :: OSI Approved :: Apache Software License
Classifier: Programming Language :: Python
Classifier: Programming Language :: Python :: 3.9
Classifier: Programming Language :: Python :: 3.10
Classifier: Programming Language :: Python :: 3.11
Classifier: Programming Language :: Python :: 3.12
Classifier: Programming Language :: Python :: Implementation :: CPython
Classifier: Programming Language :: Python :: Implementation :: PyPy
Requires-Python: >=3.9
Requires-Dist: numpy>=1.25
Requires-Dist: pandas>=1.5.3
Requires-Dist: scikit-learn>=1.4
Requires-Dist: torch>=2.0
Provides-Extra: dev
Requires-Dist: pytest-cov>=4.0; extra == 'dev'
Requires-Dist: pytest>=7.0; extra == 'dev'
Provides-Extra: extra
Requires-Dist: catboost>=1.1; extra == 'extra'
Requires-Dist: lightgbm>=3.3.0; extra == 'extra'
Requires-Dist: probmetrics>=1.0.0; extra == 'extra'
Requires-Dist: scipy>=1.13; extra == 'extra'
